mcp_neo4j_cypher/__init__.py
mcp_neo4j_cypher/server.py
mcp_neo4j_cypher/utils.py
mcp_neo4j_cypher-0.5.2.dist-info/METADATA
mcp_neo4j_cypher-0.5.2.dist-info/WHEEL
mcp_neo4j_cypher-0.5.2.dist-info/entry_points.txt
mcp_neo4j_cypher-0.5.2.dist-info/RECORD
