Metadata-Version: 2.4
Name: mcp-neo4j-cypher
Version: 0.5.2
Summary: A simple Neo4j MCP server
Requires-Python: >=3.10
Requires-Dist: fastmcp>=2.10.5
Requires-Dist: neo4j>=5.26.0
Requires-Dist: pydantic>=2.10.1
Requires-Dist: tiktoken>=0.11.0
